collective.watcherlist-4.0.0a1-py3.11-nspkg.pth
collective/watcherlist/README.rst
collective/watcherlist/__init__.py
collective/watcherlist/browser.py
collective/watcherlist/configure.zcml
collective/watcherlist/event.py
collective/watcherlist/i18n.py
collective/watcherlist/interfaces.py
collective/watcherlist/mailer.py
collective/watcherlist/triggers_handlers.py
collective/watcherlist/utils.py
collective/watcherlist/watchers.py
collective/watcherlist/actions/__init__.py
collective/watcherlist/actions/configure.zcml
collective/watcherlist/actions/vocabularies.py
collective/watcherlist/actions/watching.py
collective/watcherlist/sample/__init__.py
collective/watcherlist/sample/browser.py
collective/watcherlist/sample/configure.zcml
collective/watcherlist/sample/eventhandlers.py
collective/watcherlist/sample/form.pt
collective/watcherlist/sample/newsletter.txt
collective/watcherlist/tests/__init__.py
collective/watcherlist/tests/cornercases.txt
collective/watcherlist/tests/test_integration.py
collective/watcherlist/tests/test_unit.py
collective.watcherlist-4.0.0a1.dist-info/METADATA
collective.watcherlist-4.0.0a1.dist-info/WHEEL
collective.watcherlist-4.0.0a1.dist-info/entry_points.txt
collective.watcherlist-4.0.0a1.dist-info/namespace_packages.txt
collective.watcherlist-4.0.0a1.dist-info/top_level.txt
collective.watcherlist-4.0.0a1.dist-info/RECORD
