Metadata-Version: 2.1
Name: collective.watcherlist
Version: 4.0.0a1
Summary: Send emails from Plone to interested members (watchers)
Home-page: https://github.com/collective/collective.watcherlist
Author: Maurits van Rees
Author-email: maurits@vanrees.org
License: GPL
Keywords: Plone notifications watching
Classifier: Development Status :: 5 - Production/Stable
Classifier: Framework :: Plone
Classifier: Framework :: Plone :: 5.2
Classifier: Framework :: Plone :: 6.0
Classifier: License :: OSI Approved :: GNU General Public License (GPL)
Classifier: Programming Language :: Python
Classifier: Programming Language :: Python :: 3.8
Requires-Python: >=3.8, <4
Requires-Dist: Products.CMFPlone
Requires-Dist: plone.api
Requires-Dist: setuptools
Requires-Dist: zope.formlib
Provides-Extra: test
Requires-Dist: plone.app.testing ; extra == 'test'
